articubench/__init__.py
articubench/animation.py
articubench/benchmark_data.py
articubench/control_models.py
articubench/data/GECO/TODO.rst
articubench/data/KEC/TODO.rst
articubench/data/LICENSE.rst
articubench/data/README.rst
articubench/data/babibabubaba/TODO.rst
articubench/data/common_voice/TODO.rst
articubench/data/lexical_embedding_vectors.pkl
articubench/data/sampa_ipa_dict.pkl
articubench/data/tiny.pkl
articubench/embedding_models.py
articubench/eval_tongue_height.py
articubench/eval_tongue_tip.py
articubench/evaluate.py
articubench/gather_data.py
articubench/results/example/TODO.rst
articubench/results/results_baseline_schwa.pkl
articubench/results/results_paule_fast.pkl
articubench/results/results_paule_full_syn.pkl
articubench/results/results_segment.pkl
articubench/score.py
articubench/util.py
articubench/vocaltractlab_api/JD3.speaker
articubench/vocaltractlab_api/libVocalTractLabApi.dylib
articubench/vocaltractlab_api/libVocalTractLabApi.so
articubench-0.3.5.dist-info/LICENSE
articubench-0.3.5.dist-info/METADATA
articubench-0.3.5.dist-info/WHEEL
articubench-0.3.5.dist-info/RECORD
