Metadata-Version: 2.3
Name: articubench
Version: 0.3.5
Summary: articubench - An Articulatory Speech Synthesis Benchmark
License: GPLv3+
Author: Konstantin (Tino) Sering
Author-email: konstantin.sering@uni-tuebingen.de
Requires-Python: >=3.9,<3.14
Classifier: Development Status :: 3 - Alpha
Classifier: Environment :: Console
Classifier: Intended Audience :: Science/Research
Classifier: License :: Other/Proprietary License
Classifier: Operating System :: MacOS
Classifier: Operating System :: Microsoft :: Windows
Classifier: Operating System :: POSIX :: Linux
Classifier: Programming Language :: Python :: 3
Classifier: Programming Language :: Python :: 3.9
Classifier: Programming Language :: Python :: 3.10
Classifier: Programming Language :: Python :: 3.11
Classifier: Programming Language :: Python :: 3.12
Classifier: Programming Language :: Python :: 3.13
Classifier: Topic :: Scientific/Engineering
Classifier: Topic :: Scientific/Engineering :: Artificial Intelligence
Classifier: Topic :: Scientific/Engineering :: Information Analysis
Requires-Dist: librosa (>=0.9.0)
Requires-Dist: llvmlite (>=0.42.0)
Requires-Dist: matplotlib (>=3.7.1)
Requires-Dist: numpy (>=1.23.1)
Requires-Dist: opencv-python (>=4.11)
Requires-Dist: pandas (>=1.5.3)
Requires-Dist: paule (>=0.3.6)
Requires-Dist: praatio (>=6.0.0)
Requires-Dist: pylint (>=2.16.3)
Requires-Dist: resampy (>=0.4.2)
Requires-Dist: setuptools (>=69.1.0)
Requires-Dist: soundfile (>=0.11)
Requires-Dist: torch (>=1.7.0)
Requires-Dist: tqdm (>=4.65.0)
Project-URL: Homepage, https://articubench.readthedocs.io/en/latest/
Project-URL: Repository, https://github.com/quantling/articubench
